{"Version":"1.0.0.0","LastState":11,"Modules":[{"ModuleName":"Front Left","ModuleId":0,"Encoder":{"Id":24,"Name":"FrontLeftEncoder","Model":"CANCoder","CANbus":"7EA5929533533853202020343E1501FF","CANbusFriendly":"candrive","SelectedMotorType":null,"IsStandaloneFx":false},"SteerMotor":{"Id":8,"Name":"FrontLeftTurning","Model":"Talon FX","CANbus":"7EA5929533533853202020343E1501FF","CANbusFriendly":"candrive","SelectedMotorType":{"Name":"WCP Kraken x60","FreeSpeedRps":96.7},"IsStandaloneFx":false},"DriveMotor":{"Id":7,"Name":"FrontLeftDrive","Model":"Talon FX","CANbus":"7EA5929533533853202020343E1501FF","CANbusFriendly":"candrive","SelectedMotorType":{"Name":"WCP Kraken x60","FreeSpeedRps":96.7},"IsStandaloneFx":false},"IsEncoderInverted":false,"IsSteerInverted":true,"SelectedEncoderType":"CANcoder","EncoderOffset":-0.42822265625,"DriveMotorSelectionState":1,"SteerMotorSelectionState":1,"SteerEncoderSelectionState":1,"IsModuleValidationComplete":true,"ValidatedSteerId":8,"ValidatedDriveId":7,"ValidatedEncoderId":24,"AvailEncoders":[{"Id":21,"Name":"FrontRightEncoder","Model":"CANCoder","CANbus":"7EA5929533533853202020343E1501FF","CANbusFriendly":"candrive","SelectedMotorType":null,"IsStandaloneFx":false},{"Id":22,"Name":"BackRightEncoder","Model":"CANCoder","CANbus":"7EA5929533533853202020343E1501FF","CANbusFriendly":"candrive","SelectedMotorType":null,"IsStandaloneFx":false},{"Id":23,"Name":"BackLeftEncoder","Model":"CANCoder","CANbus":"7EA5929533533853202020343E1501FF","CANbusFriendly":"candrive","SelectedMotorType":null,"IsStandaloneFx":false},{"Id":24,"Name":"FrontLeftEncoder","Model":"CANCoder","CANbus":"7EA5929533533853202020343E1501FF","CANbusFriendly":"candrive","SelectedMotorType":null,"IsStandaloneFx":false}],"IsEncoderTypeCAN":true,"IsDeviceSelectionCompleted":true,"IsConfigurationCompleted":true,"AvailEncoderTypes":["CANcoder"]},{"ModuleName":"Front Right","ModuleId":1,"Encoder":{"Id":21,"Name":"FrontRightEncoder","Model":"CANCoder","CANbus":"7EA5929533533853202020343E1501FF","CANbusFriendly":"candrive","SelectedMotorType":null,"IsStandaloneFx":false},"SteerMotor":{"Id":2,"Name":"FrontRightTurning","Model":"Talon FX","CANbus":"7EA5929533533853202020343E1501FF","CANbusFriendly":"candrive","SelectedMotorType":{"Name":"WCP Kraken x60","FreeSpeedRps":96.7},"IsStandaloneFx":false},"DriveMotor":{"Id":1,"Name":"FrontRightDrive","Model":"Talon FX","CANbus":"7EA5929533533853202020343E1501FF","CANbusFriendly":"candrive","SelectedMotorType":{"Name":"WCP Kraken x60","FreeSpeedRps":96.7},"IsStandaloneFx":false},"IsEncoderInverted":false,"IsSteerInverted":true,"SelectedEncoderType":"CANcoder","EncoderOffset":-0.2451171875,"DriveMotorSelectionState":1,"SteerMotorSelectionState":1,"SteerEncoderSelectionState":1,"IsModuleValidationComplete":true,"ValidatedSteerId":2,"ValidatedDriveId":1,"ValidatedEncoderId":21,"AvailEncoders":[{"Id":21,"Name":"FrontRightEncoder","Model":"CANCoder","CANbus":"7EA5929533533853202020343E1501FF","CANbusFriendly":"candrive","SelectedMotorType":null,"IsStandaloneFx":false},{"Id":22,"Name":"BackRightEncoder","Model":"CANCoder","CANbus":"7EA5929533533853202020343E1501FF","CANbusFriendly":"candrive","SelectedMotorType":null,"IsStandaloneFx":false},{"Id":23,"Name":"BackLeftEncoder","Model":"CANCoder","CANbus":"7EA5929533533853202020343E1501FF","CANbusFriendly":"candrive","SelectedMotorType":null,"IsStandaloneFx":false},{"Id":24,"Name":"FrontLeftEncoder","Model":"CANCoder","CANbus":"7EA5929533533853202020343E1501FF","CANbusFriendly":"candrive","SelectedMotorType":null,"IsStandaloneFx":false}],"IsEncoderTypeCAN":true,"IsDeviceSelectionCompleted":true,"IsConfigurationCompleted":true,"AvailEncoderTypes":["CANcoder"]},{"ModuleName":"Back Left","ModuleId":2,"Encoder":{"Id":23,"Name":"BackLeftEncoder","Model":"CANCoder","CANbus":"7EA5929533533853202020343E1501FF","CANbusFriendly":"candrive","SelectedMotorType":null,"IsStandaloneFx":false},"SteerMotor":{"Id":6,"Name":"BackLeftTurning","Model":"Talon FX","CANbus":"7EA5929533533853202020343E1501FF","CANbusFriendly":"candrive","SelectedMotorType":{"Name":"WCP Kraken x60","FreeSpeedRps":96.7},"IsStandaloneFx":false},"DriveMotor":{"Id":5,"Name":"BackLeftDrive","Model":"Talon FX","CANbus":"7EA5929533533853202020343E1501FF","CANbusFriendly":"candrive","SelectedMotorType":{"Name":"WCP Kraken x60","FreeSpeedRps":96.7},"IsStandaloneFx":false},"IsEncoderInverted":false,"IsSteerInverted":true,"SelectedEncoderType":"CANcoder","EncoderOffset":-0.392822265625,"DriveMotorSelectionState":1,"SteerMotorSelectionState":1,"SteerEncoderSelectionState":1,"IsModuleValidationComplete":true,"ValidatedSteerId":6,"ValidatedDriveId":5,"ValidatedEncoderId":23,"AvailEncoders":[{"Id":21,"Name":"FrontRightEncoder","Model":"CANCoder","CANbus":"7EA5929533533853202020343E1501FF","CANbusFriendly":"candrive","SelectedMotorType":null,"IsStandaloneFx":false},{"Id":22,"Name":"BackRightEncoder","Model":"CANCoder","CANbus":"7EA5929533533853202020343E1501FF","CANbusFriendly":"candrive","SelectedMotorType":null,"IsStandaloneFx":false},{"Id":23,"Name":"BackLeftEncoder","Model":"CANCoder","CANbus":"7EA5929533533853202020343E1501FF","CANbusFriendly":"candrive","SelectedMotorType":null,"IsStandaloneFx":false},{"Id":24,"Name":"FrontLeftEncoder","Model":"CANCoder","CANbus":"7EA5929533533853202020343E1501FF","CANbusFriendly":"candrive","SelectedMotorType":null,"IsStandaloneFx":false}],"IsEncoderTypeCAN":true,"IsDeviceSelectionCompleted":true,"IsConfigurationCompleted":true,"AvailEncoderTypes":["CANcoder"]},{"ModuleName":"Back Right","ModuleId":3,"Encoder":{"Id":22,"Name":"BackRightEncoder","Model":"CANCoder","CANbus":"7EA5929533533853202020343E1501FF","CANbusFriendly":"candrive","SelectedMotorType":null,"IsStandaloneFx":false},"SteerMotor":{"Id":4,"Name":"BackRightTurning","Model":"Talon FX","CANbus":"7EA5929533533853202020343E1501FF","CANbusFriendly":"candrive","SelectedMotorType":{"Name":"WCP Kraken x60","FreeSpeedRps":96.7},"IsStandaloneFx":false},"DriveMotor":{"Id":3,"Name":"BackRightDrive","Model":"Talon FX","CANbus":"7EA5929533533853202020343E1501FF","CANbusFriendly":"candrive","SelectedMotorType":{"Name":"WCP Kraken x60","FreeSpeedRps":96.7},"IsStandaloneFx":false},"IsEncoderInverted":false,"IsSteerInverted":true,"SelectedEncoderType":"CANcoder","EncoderOffset":-0.27392578125,"DriveMotorSelectionState":1,"SteerMotorSelectionState":1,"SteerEncoderSelectionState":1,"IsModuleValidationComplete":true,"ValidatedSteerId":4,"ValidatedDriveId":3,"ValidatedEncoderId":22,"AvailEncoders":[{"Id":21,"Name":"FrontRightEncoder","Model":"CANCoder","CANbus":"7EA5929533533853202020343E1501FF","CANbusFriendly":"candrive","SelectedMotorType":null,"IsStandaloneFx":false},{"Id":22,"Name":"BackRightEncoder","Model":"CANCoder","CANbus":"7EA5929533533853202020343E1501FF","CANbusFriendly":"candrive","SelectedMotorType":null,"IsStandaloneFx":false},{"Id":23,"Name":"BackLeftEncoder","Model":"CANCoder","CANbus":"7EA5929533533853202020343E1501FF","CANbusFriendly":"candrive","SelectedMotorType":null,"IsStandaloneFx":false},{"Id":24,"Name":"FrontLeftEncoder","Model":"CANCoder","CANbus":"7EA5929533533853202020343E1501FF","CANbusFriendly":"candrive","SelectedMotorType":null,"IsStandaloneFx":false}],"IsEncoderTypeCAN":true,"IsDeviceSelectionCompleted":true,"IsConfigurationCompleted":true,"AvailEncoderTypes":["CANcoder"]}],"SwerveOptions":{"kSpeedAt12Volts":5.958135187288162,"Gyro":{"Id":25,"Name":"Pigeon 2","Model":"Pigeon 2","CANbus":"7EA5929533533853202020343E1501FF","CANbusFriendly":"candrive","SelectedMotorType":null,"IsStandaloneFx":false},"IsValidGyroCANbus":true,"VerticalTrackSizeInches":20.0,"HorizontalTrackSizeInches":20.0,"WheelRadiusInches":2.0,"IsLeftSideInverted":false,"IsRightSideInverted":true,"SwerveModuleType":4,"SwerveModuleConfiguration":{"ModuleBrand":4,"DriveRatio":5.357142857142857,"SteerRatio":21.428571428571427,"CouplingRatio":3.125,"CustomName":"L3 16T"},"HasVerifiedSteer":true,"HasVerifiedDrive":true,"IsValidConfiguration":true}}